django_fast_treenode-3.2.6.dist-info/licenses/LICENSE
treenode/__init__.py
treenode/apps.py
treenode/cache.py
treenode/forms.py
treenode/middleware.py
treenode/settings.py
treenode/signals.py
treenode/tests.py
treenode/urls.py
treenode/version.py
treenode/widgets.py
treenode/admin/__init__.py
treenode/admin/admin.py
treenode/admin/changelist.py
treenode/admin/exporter.py
treenode/admin/importer.py
treenode/admin/mixin.py
treenode/managers/__init__.py
treenode/managers/managers.py
treenode/managers/queries.py
treenode/managers/tasks.py
treenode/models/__init__.py
treenode/models/decorators.py
treenode/models/factory.py
treenode/models/models.py
treenode/models/mixins/__init__.py
treenode/models/mixins/ancestors.py
treenode/models/mixins/children.py
treenode/models/mixins/descendants.py
treenode/models/mixins/family.py
treenode/models/mixins/logical.py
treenode/models/mixins/node.py
treenode/models/mixins/properties.py
treenode/models/mixins/roots.py
treenode/models/mixins/search.py
treenode/models/mixins/siblings.py
treenode/models/mixins/tree.py
treenode/models/mixins/update.py
treenode/static/.gitkeep
treenode/static/treenode/.gitkeep
treenode/static/treenode/css/.gitkeep
treenode/static/treenode/css/tree_widget.css
treenode/static/treenode/css/treenode_admin.css
treenode/static/treenode/css/treenode_tabs.css
treenode/static/treenode/js/.gitkeep
treenode/static/treenode/js/lz-string.min.js
treenode/static/treenode/js/tree_widget.js
treenode/static/treenode/js/treenode_admin.js
treenode/static/treenode/vendors/.gitkeep
treenode/static/treenode/vendors/jquery-ui/.gitkeep
treenode/static/treenode/vendors/jquery-ui/AUTHORS.txt
treenode/static/treenode/vendors/jquery-ui/LICENSE.txt
treenode/static/treenode/vendors/jquery-ui/index.html
treenode/static/treenode/vendors/jquery-ui/jquery-ui.css
treenode/static/treenode/vendors/jquery-ui/jquery-ui.js
treenode/static/treenode/vendors/jquery-ui/jquery-ui.min.css
treenode/static/treenode/vendors/jquery-ui/jquery-ui.min.js
django_fast_treenode-3.2.6.dist-info/METADATA
django_fast_treenode-3.2.6.dist-info/WHEEL
django_fast_treenode-3.2.6.dist-info/top_level.txt
django_fast_treenode-3.2.6.dist-info/RECORD
