Metadata-Version: 2.4
Name: django-fast-treenode
Version: 3.2.6
Summary: Treenode Framework for supporting tree (hierarchical) data structure in Django projects
Home-page: https://django-fast-treenode.readthedocs.io/
Author: Timur Kady
Author-email: Timur Kady <timurkady@yandex.com>
License: MIT License
Project-URL: Homepage, https://github.com/TimurKady/django-fast-treenode
Project-URL: Documentation, https://django-fast-treenode.readthedocs.io/
Project-URL: Source, https://github.com/TimurKady/django-fast-treenode
Project-URL: Issues, https://github.com/TimurKady/django-fast-treenode/issues
Classifier: Development Status :: 5 - Production/Stable
Classifier: Intended Audience :: Developers
Classifier: Programming Language :: Python :: 3
Classifier: Programming Language :: Python :: 3.9
Classifier: Programming Language :: Python :: 3.10
Classifier: Programming Language :: Python :: 3.11
Classifier: Programming Language :: Python :: 3.12
Classifier: Programming Language :: Python :: 3.13
Classifier: Programming Language :: Python :: 3.14
Classifier: Framework :: Django
Classifier: Framework :: Django :: 4.0
Classifier: Framework :: Django :: 4.1
Classifier: Framework :: Django :: 4.2
Classifier: Framework :: Django :: 5.0
Classifier: Framework :: Django :: 5.1
Classifier: Framework :: Django :: 5.2
Classifier: License :: OSI Approved :: MIT License
Classifier: Operating System :: OS Independent
Requires-Python: >=3.9
License-File: LICENSE
Requires-Dist: Django>=5.0
Requires-Dist: msgpack>=1.0.0
Requires-Dist: openpyxl>=3.0.0
Requires-Dist: pyyaml>=5.1
Requires-Dist: PyJWT>=2.0
Dynamic: author
Dynamic: home-page
Dynamic: license-file
Dynamic: requires-python
